merklelib/__init__.py
merklelib/compat.py
merklelib/format.py
merklelib/merkle.py
merklelib/utils.py
np_merklelib-1.1.dist-info/LICENSE
np_merklelib-1.1.dist-info/METADATA
np_merklelib-1.1.dist-info/WHEEL
np_merklelib-1.1.dist-info/top_level.txt
np_merklelib-1.1.dist-info/RECORD
