Metadata-Version: 2.1
Name: np-merklelib
Version: 1.1
Summary: Merkle tree and its variations for easier data verification.
Home-page: https://github.com/pritchardn/merklelib
Author: Nicholas J. Pritchard
Author-email: professional@nicpritchard.com
License: MIT
Classifier: Intended Audience :: Developers
Classifier: Operating System :: OS Independent
Classifier: Programming Language :: Python
Classifier: Programming Language :: Python :: 3
Classifier: Programming Language :: Python :: 3.4
Classifier: Programming Language :: Python :: 3.5
Classifier: Programming Language :: Python :: 3.6
Classifier: Programming Language :: Python :: 3.7
Classifier: Programming Language :: Python :: 3.8
Classifier: Programming Language :: Python :: 3.9
Classifier: Programming Language :: Python :: 3.10
Requires-Python: >=3.6
License-File: LICENSE
Requires-Dist: six
Requires-Dist: future-fstrings
Requires-Dist: anytree
